wayback_machine_archiver/__init__.py
wayback_machine_archiver/archiver.py
wayback_machine_archiver/cli.py
wayback_machine_archiver/clients.py
wayback_machine_archiver/py.typed
wayback_machine_archiver/sitemaps.py
wayback_machine_archiver/workflow.py
wayback_machine_archiver-3.5.0.dist-info/licenses/LICENSE
wayback_machine_archiver-3.5.0.dist-info/METADATA
wayback_machine_archiver-3.5.0.dist-info/WHEEL
wayback_machine_archiver-3.5.0.dist-info/entry_points.txt
wayback_machine_archiver-3.5.0.dist-info/top_level.txt
wayback_machine_archiver-3.5.0.dist-info/RECORD
