Metadata-Version: 2.4
Name: wayback-machine-archiver
Version: 3.5.0
Summary: A Python script to submit web pages to the Wayback Machine for archiving.
Author-email: Alexander Gude <alex.public.account@gmail.com>
License: # MIT License (MIT)
Project-URL: Homepage, https://github.com/agude/wayback-machine-archiver
Keywords: Internet Archive,Wayback Machine
Classifier: Development Status :: 5 - Production/Stable
Classifier: Environment :: Console
Classifier: Intended Audience :: System Administrators
Classifier: License :: OSI Approved :: MIT License
Classifier: Natural Language :: English
Classifier: Operating System :: OS Independent
Classifier: Programming Language :: Python
Classifier: Topic :: Utilities
Requires-Python: >=3.8
License-File: LICENSE
Requires-Dist: python-dotenv
Requires-Dist: requests
Requires-Dist: urllib3
Provides-Extra: dev
Requires-Dist: pytest; extra == "dev"
Requires-Dist: requests-mock; extra == "dev"
Requires-Dist: bump-my-version; extra == "dev"
Dynamic: license-file
